explainer/README.md
explainer/version.py
explainer/attributions/README.md
explainer/attributions/__init__.py
explainer/attributions/attributions.py
explainer/attributions/attributions_info.py
explainer/attributions/plots.py
explainer/attributions/pt_attributions.py
explainer/attributions/widgets.py
explainer/cam/README.md
explainer/cam/__init__.py
explainer/cam/cam.py
explainer/cam/pt_cam.py
explainer/cam/tf_cam.py
explainer/metrics/README.md
explainer/metrics/__init__.py
explainer/metrics/metrics.py
explainer/tests/__init__.py
explainer/tests/conftest.py
explainer/tests/pytest.ini
explainer/tests/test_attributions.py
explainer/tests/test_cam.py
explainer/tests/test_metrics.py
explainer/tests/test_requirements.txt
explainer/utils/types.py
explainer/utils/graphics/__init__.py
explainer/utils/graphics/info.py
explainer/utils/model/__init__.py
explainer/utils/model/model_framework.py
model_card_gen/README.md
model_card_gen/__init__.py
model_card_gen/base_model_card_field.py
model_card_gen/model_card.py
model_card_gen/model_card_gen.py
model_card_gen/validation.py
model_card_gen/version.py
model_card_gen/analyze/__init__.py
model_card_gen/analyze/analyzer.py
model_card_gen/analyze/analyzer_factory.py
model_card_gen/analyze/pandas_analyzer.py
model_card_gen/analyze/tf_analyzer.py
model_card_gen/analyze/torch_analyzer.py
model_card_gen/datasets/__init__.py
model_card_gen/datasets/datasets.py
model_card_gen/datasets/tf_datasets.py
model_card_gen/datasets/torch_datasets.py
model_card_gen/docs/examples/__init__.py
model_card_gen/docs/examples/html/compas_model_card.html
model_card_gen/docs/examples/json/model_card_compas.json
model_card_gen/docs/examples/json/model_card_example.json
model_card_gen/graphics/__init__.py
model_card_gen/graphics/add_graphics.py
model_card_gen/graphics/plotly_graphics.py
model_card_gen/graphics/plotly_utils.py
model_card_gen/schema/v0.0.1/model_card.schema.json
model_card_gen/template/html/default_template.html.jinja
intel_xai-0.6.0.dist-info/LICENSE
intel_xai-0.6.0.dist-info/METADATA
intel_xai-0.6.0.dist-info/WHEEL
intel_xai-0.6.0.dist-info/top_level.txt
intel_xai-0.6.0.dist-info/RECORD
