Metadata-Version: 2.1
Name: intel-xai
Version: 0.6.0
Summary: Intel® Explainable AI Tools
Home-page: https://github.com/IntelAI/intel-xai-tools
Author: IntelAI
Author-email: IntelAI@intel.com
License: Apache 2.0
Keywords: XAI,explainer
Platform: any
Classifier: Development Status :: 5 - Production/Stable
Classifier: Environment :: Console
Classifier: Intended Audience :: Developers
Classifier: Intended Audience :: Education
Classifier: Intended Audience :: Science/Research
Classifier: License :: OSI Approved :: Apache Software License
Classifier: Operating System :: OS Independent
Classifier: Programming Language :: Python
Classifier: Programming Language :: Python :: 3
Classifier: Programming Language :: Python :: 3 :: Only
Classifier: Topic :: Software Development :: Libraries :: Python Modules
Classifier: Topic :: Scientific/Engineering
Classifier: Topic :: Scientific/Engineering :: Mathematics
Classifier: Topic :: Scientific/Engineering :: Artificial Intelligence
Requires-Python: >=3.8
License-File: LICENSE
Requires-Dist: captum ==0.6.0
Requires-Dist: intel-tensorflow ==2.13.0
Requires-Dist: ipywidgets ==7.8.1
Requires-Dist: opencv-python ==4.8.0.76
Requires-Dist: plotly ==5.17.0
Requires-Dist: scikit-plot ==0.3.7
Requires-Dist: shap ==0.42.1
Requires-Dist: torch ==2.0.1
Requires-Dist: transformers ==4.33.2
Requires-Dist: grad-cam ==1.4.8
Requires-Dist: pandas ==1.5.3
Requires-Dist: scikit-learn ==1.3.1
Requires-Dist: seaborn ==0.12.2
Requires-Dist: Jinja2 ==3.1.2
Requires-Dist: absl-py ==1.4.0
Requires-Dist: attrs ==21.4.0
Requires-Dist: dataclasses ==0.6
Requires-Dist: grpcio-status ==1.48.2
Requires-Dist: joblib ==1.3.2
Requires-Dist: jsonschema[format-nongpl] ==4.17.3
Requires-Dist: protobuf ==3.20.3
Requires-Dist: semantic-version ==2.10.0
Requires-Dist: numpy ==1.22.4 ; python_version < "3.10"
Requires-Dist: tensorflow-data-validation ==1.13.0 ; python_version < "3.10"
Requires-Dist: tensorflow-model-analysis ==0.44.0 ; python_version < "3.10"
Requires-Dist: numpy ==1.24.3 ; python_version == "3.10"
Requires-Dist: tensorflow-data-validation ==1.14.0 ; python_version == "3.10"
Requires-Dist: tensorflow-model-analysis ==0.45.0 ; python_version == "3.10"
Requires-Dist: scipy ==1.10.1 ; python_version == "3.8"
Requires-Dist: matplotlib ==3.7.3 ; python_version == "3.8"
Requires-Dist: scipy ==1.11.2 ; python_version > "3.8"
Requires-Dist: matplotlib ==3.8.0 ; python_version > "3.8"
Provides-Extra: pytorch
Requires-Dist: torch ==2.0.1 ; extra == 'pytorch'
Requires-Dist: torchvision ==0.15.2 ; extra == 'pytorch'
Provides-Extra: test
Requires-Dist: deepdiff ==6.5.0 ; extra == 'test'
Requires-Dist: pytest ==7.4.2 ; extra == 'test'
Requires-Dist: tensorflow-hub ==0.14.0 ; extra == 'test'
Requires-Dist: torch ==2.0.1 ; extra == 'test'
Requires-Dist: torchvision ==0.15.2 ; extra == 'test'
Requires-Dist: datasets ==2.10.1 ; (python_version < "3.10") and extra == 'test'
Requires-Dist: datasets ==2.14.4 ; (python_version == "3.10") and extra == 'test'
